{
  "tests": [
    {
      "name": "This is an empty test-case!",
      "setup": "echo \"Configuring... Wait a minute...\"",
      "run": "echo \"Success! You got 1 point!\"",
      "input": "",
      "output": "",
      "comparison": "exact",
      "timeout": 1,
      "points": 1
    },
    {
      "name": "Passing test-case",
      "setup": "",
      "run": "ctest -VVV --output-on-failure --test-dir build -R \"Passing test-case\"",
      "input": "",
      "output": "",
      "comparison": "exact",
      "timeout": 1,
      "points": 1
    },
    {
      "name": "Failing test-case",
      "setup": "",
      "run": "ctest -VVV --output-on-failure --test-dir build -R \"Failing test-case\"",
      "input": "",
      "output": "",
      "comparison": "exact",
      "timeout": 1,
      "points": 1
    }
  ]
}
